{
    "1password-cli-linux": {
        "cargoLocks": null,
        "date": null,
        "extract": null,
        "name": "1password-cli-linux",
        "passthru": null,
        "pinned": false,
        "src": {
            "sha256": "sha256-MsBSjJi7hJbS1wU3lVeywRrhGAZkoqxRb4FTg8fFN00=",
            "type": "tarball",
            "url": "https://cache.agilebits.com/dist/1P/op2/pkg/v2.30.3/op_linux_amd64_v2.30.3.zip"
        },
        "version": "v2.30.3"
    },
    "deploy-rs": {
        "cargoLocks": null,
        "date": null,
        "extract": null,
        "name": "deploy-rs",
        "passthru": null,
        "pinned": false,
        "src": {
            "deepClone": false,
            "fetchSubmodules": false,
            "leaveDotGit": false,
            "name": null,
            "owner": "serokell",
            "repo": "deploy-rs",
            "rev": "master",
            "sha256": "sha256-hXh76y/wDl15almBcqvjryB50B0BaiXJKk20f314RoE=",
            "sparseCheckout": [],
            "type": "github"
        },
        "version": "master"
    },
    "devenv": {
        "cargoLocks": null,
        "date": null,
        "extract": null,
        "name": "devenv",
        "passthru": null,
        "pinned": false,
        "src": {
            "deepClone": false,
            "fetchSubmodules": false,
            "leaveDotGit": false,
            "name": null,
            "owner": "cachix",
            "repo": "devenv",
            "rev": "latest",
            "sha256": "sha256-CEVWxRaln3sp0541QpMfcfmI2w+RN72UgNLV5Dy9sco=",
            "sparseCheckout": [],
            "type": "github"
        },
        "version": "latest"
    },
    "dotnet-script": {
        "cargoLocks": null,
        "date": null,
        "extract": null,
        "name": "dotnet-script",
        "passthru": null,
        "pinned": false,
        "src": {
            "sha256": "sha256-Pc8+hja4OUajMLCOlieVLLvRMj74+OmecYlv3YyOvwo=",
            "type": "tarball",
            "url": "https://github.com/dotnet-script/dotnet-script/releases/download/1.6.0/dotnet-script.1.6.0.zip"
        },
        "version": "1.6.0"
    },
    "font-firacode": {
        "cargoLocks": null,
        "date": null,
        "extract": null,
        "name": "font-firacode",
        "passthru": null,
        "pinned": false,
        "src": {
            "name": null,
            "sha256": "sha256-CUmRW6jrJNif2T0Qp/9iP0KDDXxf/D7L+WDk7K0+Pnk=",
            "type": "url",
            "url": "https://github.com/tonsky/FiraCode/releases/download/6.2/Fira_Code_v6.2.zip"
        },
        "version": "6.2"
    },
    "goctl": {
        "cargoLocks": null,
        "date": null,
        "extract": null,
        "name": "goctl",
        "passthru": null,
        "pinned": false,
        "src": {
            "deepClone": false,
            "fetchSubmodules": false,
            "leaveDotGit": false,
            "name": null,
            "owner": "zeromicro",
            "repo": "go-zero",
            "rev": "v1.8.4",
            "sha256": "sha256-N0U/8YbqhyD5kb14lq8JKWwfYHUZ57Z/KZyIf6kKl0U=",
            "sparseCheckout": [],
            "type": "github"
        },
        "version": "v1.8.4"
    },
    "kratos": {
        "cargoLocks": null,
        "date": null,
        "extract": null,
        "name": "kratos",
        "passthru": null,
        "pinned": false,
        "src": {
            "deepClone": false,
            "fetchSubmodules": false,
            "leaveDotGit": false,
            "name": null,
            "owner": "go-kratos",
            "repo": "kratos",
            "rev": "v2.8.4",
            "sha256": "sha256-N0jNIrFOTCOICL7pM1SZQJQd80hedG7XS/mrc8LrEsY=",
            "sparseCheckout": [],
            "type": "github"
        },
        "version": "v2.8.4"
    },
    "lix": {
        "cargoLocks": null,
        "date": null,
        "extract": null,
        "name": "lix",
        "passthru": null,
        "pinned": false,
        "src": {
            "deepClone": false,
            "fetchSubmodules": false,
            "leaveDotGit": false,
            "name": null,
            "owner": "lix-project",
            "repo": "lix",
            "rev": "2.93.1",
            "sha256": "sha256-LmQhjQ7c+AOkwhvR9GFgJOy8oHW35MoQRELtrwyVnPw=",
            "sparseCheckout": [],
            "type": "github"
        },
        "version": "2.93.1"
    },
    "microsoft-edge": {
        "cargoLocks": null,
        "date": null,
        "extract": null,
        "name": "microsoft-edge",
        "passthru": null,
        "pinned": false,
        "src": {
            "name": null,
            "sha256": "sha256-SC8h6UQ/ee5ZlQWAZsmC1Co5Ky4kaXuoMpvVZtTIMHQ=",
            "type": "url",
            "url": "https://packages.microsoft.com/repos/edge/pool/main/m/microsoft-edge-stable/microsoft-edge-stable_137.0.3296.93-1_amd64.deb"
        },
        "version": "137.0.3296.93"
    },
    "nix-vscode-extensions": {
        "cargoLocks": null,
        "date": null,
        "extract": null,
        "name": "nix-vscode-extensions",
        "passthru": null,
        "pinned": false,
        "src": {
            "deepClone": false,
            "fetchSubmodules": false,
            "leaveDotGit": false,
            "name": null,
            "owner": "nix-community",
            "repo": "nix-vscode-extensions",
            "rev": "master",
            "sha256": "sha256-kgaDkd9Ti1hNNtWRJrXbrhBnBmx72y3uR3mI6OIYjwQ=",
            "sparseCheckout": [],
            "type": "github"
        },
        "version": "master"
    },
    "pwndbg": {
        "cargoLocks": null,
        "date": null,
        "extract": null,
        "name": "pwndbg",
        "passthru": null,
        "pinned": false,
        "src": {
            "deepClone": false,
            "fetchSubmodules": false,
            "leaveDotGit": false,
            "name": null,
            "owner": "pwndbg",
            "repo": "pwndbg",
            "rev": "2025.05.30",
            "sha256": "sha256-Y8tERNTdMrRj07d3vTN2LvEUsZUhJ4lEEqWMzF5QohU=",
            "sparseCheckout": [],
            "type": "github"
        },
        "version": "2025.05.30"
    },
    "python": {
        "cargoLocks": null,
        "date": null,
        "extract": null,
        "name": "python",
        "passthru": null,
        "pinned": false,
        "src": {
            "deepClone": false,
            "fetchSubmodules": false,
            "leaveDotGit": false,
            "name": null,
            "owner": "cachix",
            "repo": "nixpkgs-python",
            "rev": "main",
            "sha256": "sha256-koLwnVjVrR4yS2ea1owMj6ps2sOhH67ObTIld9H27Yo=",
            "sparseCheckout": [],
            "type": "github"
        },
        "version": "main"
    },
    "shellfirm": {
        "cargoLocks": null,
        "date": null,
        "extract": null,
        "name": "shellfirm",
        "passthru": null,
        "pinned": false,
        "src": {
            "deepClone": false,
            "fetchSubmodules": false,
            "leaveDotGit": false,
            "name": null,
            "owner": "kaplanelad",
            "repo": "shellfirm",
            "rev": "v0.2.11",
            "sha256": "sha256-jwrH2/EwiB33YoTC+pGO4Jm3tC4dp1DLZLZvhKvUy30=",
            "sparseCheckout": [],
            "type": "github"
        },
        "version": "v0.2.11"
    },
    "trzsz": {
        "cargoLocks": null,
        "date": null,
        "extract": null,
        "name": "trzsz",
        "passthru": null,
        "pinned": false,
        "src": {
            "deepClone": false,
            "fetchSubmodules": false,
            "leaveDotGit": false,
            "name": null,
            "owner": "trzsz",
            "repo": "trzsz-go",
            "rev": "v1.1.8",
            "sha256": "sha256-g1fbgKTFS9aPAmnTeFYoymrDEoZ6BtzUhA2Z9SNYbsU=",
            "sparseCheckout": [],
            "type": "github"
        },
        "version": "v1.1.8"
    },
    "trzsz-ssh": {
        "cargoLocks": null,
        "date": null,
        "extract": null,
        "name": "trzsz-ssh",
        "passthru": null,
        "pinned": false,
        "src": {
            "deepClone": false,
            "fetchSubmodules": false,
            "leaveDotGit": false,
            "name": null,
            "owner": "trzsz",
            "repo": "trzsz-ssh",
            "rev": "v0.1.22",
            "sha256": "sha256-VvPdWRP+lrhho+Bk5rT9pktEvKe01512WoDfAu5d868=",
            "sparseCheckout": [],
            "type": "github"
        },
        "version": "v0.1.22"
    },
    "vscode-extension-kotlin-lsp": {
        "cargoLocks": null,
        "date": null,
        "extract": null,
        "name": "vscode-extension-kotlin-lsp",
        "passthru": null,
        "pinned": false,
        "src": {
            "name": "kotlin-lsp-0.252.17811.zip",
            "sha256": "sha256-jv+90PC2WQfBvvRe4XMJsMJdVFuW1HCho1qTY2NuNko=",
            "type": "url",
            "url": "https://download-cdn.jetbrains.com/kotlin-lsp/0.252.17811/kotlin-0.252.17811.vsix"
        },
        "version": "0.252.17811"
    }
}